[
    {
        "author_name": "Oscar L Villalon",
        "author_url": "https://medium.com/@olvc89",
        "published_at": "2025-04-30 12:10:16.276000",
        "reading_time_minutes": 18.379245283018868,
        "story_url": "https://medium.com/globant/how-to-pass-runtime-parameters-to-tasks-in-airflow-b970e33f8a0b",
        "subtitle": "A deep dive",
        "title": "How to pass runtime parameters to tasks in Airflow",
        "extraction_id": "c5c44132-ea9e-4585-adc0-ec835716aaac",
        "extracted_at": "2025-05-16 06:29:12.227681",
        "extracted_at_epoch": 1747376952,
        "extraction_url": "https://medium.com/tag/apache-airflow/archive",
        "tag": "apache-airflow"
    },
    {
        "author_name": "Nur Yaumi",
        "author_url": "https://medium.com/@nuryaumi10",
        "published_at": "2025-04-02 02:20:22.037000",
        "reading_time_minutes": 10.19937106918239,
        "story_url": "https://medium.com/@nuryaumi10/my-journey-to-creating-my-first-apache-airflow-etl-weather-forecast-data-pipeline-115090457b93",
        "subtitle": "I’ve experienced building an ETL (extract, transform, and load) pipeline using Python to process over 1 million records but the process is…",
        "title": "My Journey to Automating a Weather Forecast ETL Pipeline with Apache Airflow",
        "extraction_id": "c5c44132-ea9e-4585-adc0-ec835716aaac",
        "extracted_at": "2025-05-16 06:29:12.227681",
        "extracted_at_epoch": 1747376952,
        "extraction_url": "https://medium.com/tag/apache-airflow/archive",
        "tag": "apache-airflow"
    },
    {
        "author_name": "Vijay Gadhave",
        "author_url": "https://medium.com/@vijaygadhave2014",
        "published_at": "2025-04-12 10:11:51.832000",
        "reading_time_minutes": 4.064150943396227,
        "story_url": "https://medium.com/@vijaygadhave2014/apache-airflow-sensors-unlocking-event-driven-scalable-workflows-4c3724334da8",
        "subtitle": "Note: If you’re not a medium member, CLICK HERE",
        "title": "Apache Airflow Sensors: Unlocking Event‑Driven, Scalable Workflows",
        "extraction_id": "c5c44132-ea9e-4585-adc0-ec835716aaac",
        "extracted_at": "2025-05-16 06:29:12.227681",
        "extracted_at_epoch": 1747376952,
        "extraction_url": "https://medium.com/tag/apache-airflow/archive",
        "tag": "apache-airflow"
    },
    {
        "author_name": "Vijay Gadhave",
        "author_url": "https://medium.com/@vijaygadhave2014",
        "published_at": "2025-04-12 09:58:38.566000",
        "reading_time_minutes": 3.3795597484276727,
        "story_url": "https://medium.com/@vijaygadhave2014/hook-line-and-sinker-how-airflow-hooks-saved-my-sanity-1339f3e3fd23",
        "subtitle": "Note: If you’re not a medium member, CLICK HERE",
        "title": "Hook, Line, and Sinker: How Airflow Hooks Saved My Sanity",
        "extraction_id": "c5c44132-ea9e-4585-adc0-ec835716aaac",
        "extracted_at": "2025-05-16 06:29:12.227681",
        "extracted_at_epoch": 1747376952,
        "extraction_url": "https://medium.com/tag/apache-airflow/archive",
        "tag": "apache-airflow"
    },
    {
        "author_name": "Nur Yaumi",
        "author_url": "https://medium.com/@nuryaumi10",
        "published_at": "2025-04-26 23:09:30.018000",
        "reading_time_minutes": 3.6820754716981137,
        "story_url": "https://medium.com/@nuryaumi10/implement-data-validation-on-etl-workflow-using-apache-airflow-631013583448",
        "subtitle": "After successfully building an automated data pipeline using Apache Airflow, we need to ensure our data accuracy. For my use case on…",
        "title": "Implement Data Validation on ETL Workflow using Apache Airflow",
        "extraction_id": "c5c44132-ea9e-4585-adc0-ec835716aaac",
        "extracted_at": "2025-05-16 06:29:12.227681",
        "extracted_at_epoch": 1747376952,
        "extraction_url": "https://medium.com/tag/apache-airflow/archive",
        "tag": "apache-airflow"
    },
    {
        "author_name": "Abhishek Anand",
        "author_url": "https://medium.com/@abhishekanandten",
        "published_at": "2025-05-05 00:37:01.644000",
        "reading_time_minutes": 1.9342767295597485,
        "story_url": "https://medium.com/@abhishekanandten/building-a-reusable-data-pipeline-framework-with-pyspark-and-airflow-part-1-de78b79020ba",
        "subtitle": "Introduction — The Pipeline Problem",
        "title": "Building a Reusable Data Pipeline Framework with PySpark and Airflow (Part 1)",
        "extraction_id": "c5c44132-ea9e-4585-adc0-ec835716aaac",
        "extracted_at": "2025-05-16 06:29:12.227681",
        "extracted_at_epoch": 1747376952,
        "extraction_url": "https://medium.com/tag/apache-airflow/archive",
        "tag": "apache-airflow"
    },
    {
        "author_name": "Shantam Sultania",
        "author_url": "https://medium.com/@bihari-engineer",
        "published_at": "2025-04-16 20:06:03.192000",
        "reading_time_minutes": 2.108490566037736,
        "story_url": "https://bihari-engineer.medium.com/chronicles-00-foundations-of-orchestration-f212611ac0da",
        "subtitle": "✈️ Control Tower Chronicles “Where automation ends and orchestration begins.”",
        "title": "Chronicles#00 Foundations of Orchestration",
        "extraction_id": "c5c44132-ea9e-4585-adc0-ec835716aaac",
        "extracted_at": "2025-05-16 06:29:12.227681",
        "extracted_at_epoch": 1747376952,
        "extraction_url": "https://medium.com/tag/apache-airflow/archive",
        "tag": "apache-airflow"
    },
    {
        "author_name": "Sriw World of Coding",
        "author_url": "https://medium.com/@sriwworldofcoding",
        "published_at": "2025-04-25 11:29:13.248000",
        "reading_time_minutes": 1.5547169811320753,
        "story_url": "https://medium.com/@sriwworldofcoding/apache-airflow-bootcamp-hands-on-workflow-automation-f14ff6917d73",
        "subtitle": "Hey everyone!\nI just wanted to take a moment today to say a massive thank you to each and every one of you who has enrolled in my Udemy…",
        "title": "Apache Airflow Bootcamp: Hands-On Workflow Automation",
        "extraction_id": "c5c44132-ea9e-4585-adc0-ec835716aaac",
        "extracted_at": "2025-05-16 06:29:12.227681",
        "extracted_at_epoch": 1747376952,
        "extraction_url": "https://medium.com/tag/apache-airflow/archive",
        "tag": "apache-airflow"
    },
    {
        "author_name": "Venkatesh Prabhu",
        "author_url": "https://medium.com/@venkateshprabhu",
        "published_at": "2025-04-29 04:17:12.947000",
        "reading_time_minutes": 6.9820754716981135,
        "story_url": "https://python.plainenglish.io/airflow-3-0-whats-new-8154f375835f",
        "subtitle": "Discover the most powerful updates in Apache Airflow 3.0 — from better DAG performance to future-ready orchestration.",
        "title": "🌀Everything You Need to Know About Airflow 3.0",
        "extraction_id": "c5c44132-ea9e-4585-adc0-ec835716aaac",
        "extracted_at": "2025-05-16 06:29:12.227681",
        "extracted_at_epoch": 1747376952,
        "extraction_url": "https://medium.com/tag/apache-airflow/archive",
        "tag": "apache-airflow"
    },
    {
        "author_name": "Pranay Gawas",
        "author_url": "https://medium.com/@pranaygawas11",
        "published_at": "2025-04-21 01:16:32.956000",
        "reading_time_minutes": 9.445283018867924,
        "story_url": "https://medium.com/@pranaygawas11/event-driven-data-pipelines-part-1-building-with-airflow-snowflake-aws-lambda-sqs-and-s3-9ec064197e64",
        "subtitle": "Embarking on a journey to modernize data workflows, I recently challenged myself to build an event-driven data pipeline from scratch. I…",
        "title": "Event-Driven Data Pipelines Part 1: Building with Airflow, Snowflake, AWS Lambda, SQS, and S3.",
        "extraction_id": "c5c44132-ea9e-4585-adc0-ec835716aaac",
        "extracted_at": "2025-05-16 06:29:12.227681",
        "extracted_at_epoch": 1747376952,
        "extraction_url": "https://medium.com/tag/apache-airflow/archive",
        "tag": "apache-airflow"
    },
    {
        "author_name": "Anil Jain | AI / ML Architect | Data Architect",
        "author_url": "https://medium.com/@anil.jain.baba",
        "published_at": "2025-04-05 14:08:51.381000",
        "reading_time_minutes": 6.733962264150944,
        "story_url": "https://medium.com/@anil.jain.baba/data-pipeline-strategy-using-airtflow-and-snowflake-25c0630ebebb",
        "subtitle": "1. Key Points",
        "title": "Data Pipeline Strategy Using Airflow and Snowflake",
        "extraction_id": "c5c44132-ea9e-4585-adc0-ec835716aaac",
        "extracted_at": "2025-05-16 06:29:12.227681",
        "extracted_at_epoch": 1747376952,
        "extraction_url": "https://medium.com/tag/apache-airflow/archive",
        "tag": "apache-airflow"
    },
    {
        "author_name": "Adrian Mróz",
        "author_url": "https://medium.com/@adrianmroz.7",
        "published_at": "2025-05-14 13:03:52.723000",
        "reading_time_minutes": 16.637735849056604,
        "story_url": "https://medium.com/@adrianmroz.7/optimising-airflow-cutting-dag-parse-time-from-60-s-to-milliseconds-a-practical-guide-part-1-d15081f419ae",
        "subtitle": "Ever stared at your Airflow UI, waiting for DAGs to load, or noticed your scheduler seems to be perpetually lagging? You might be…",
        "title": "Optimising Airflow: Cutting DAG parse time from 60 s to milliseconds — a practical guide (Part 1)",
        "extraction_id": "c5c44132-ea9e-4585-adc0-ec835716aaac",
        "extracted_at": "2025-05-16 06:29:12.227681",
        "extracted_at_epoch": 1747376952,
        "extraction_url": "https://medium.com/tag/apache-airflow/archive",
        "tag": "apache-airflow"
    },
    {
        "author_name": "Clay Gambetti",
        "author_url": "https://medium.com/@cmgambetti",
        "published_at": "2025-05-14 02:43:13.766000",
        "reading_time_minutes": 2.4852201257861637,
        "story_url": "https://blog.det.life/dbt-in-practice-when-it-works-and-when-it-doesnt-adba8a7a9bd2",
        "subtitle": "Lessons from Real-World Implementations",
        "title": "dbt in Practice: When It Works and When It Doesn’t",
        "extraction_id": "c5c44132-ea9e-4585-adc0-ec835716aaac",
        "extracted_at": "2025-05-16 06:29:12.227681",
        "extracted_at_epoch": 1747376952,
        "extraction_url": "https://medium.com/tag/apache-airflow/archive",
        "tag": "apache-airflow"
    },
    {
        "author_name": "Vijay Gadhave",
        "author_url": "https://medium.com/@vijaygadhave2014",
        "published_at": "2025-05-06 06:47:37.935000",
        "reading_time_minutes": 3.4738993710691823,
        "story_url": "https://medium.com/@vijaygadhave2014/master-kubernetes-apache-airflow-for-scalable-data-engineering-16e7e94727cf",
        "subtitle": "Note: If you’re not a medium member, CLICK HERE",
        "title": "Master Kubernetes & Apache Airflow for Scalable Data Engineering",
        "extraction_id": "c5c44132-ea9e-4585-adc0-ec835716aaac",
        "extracted_at": "2025-05-16 06:29:12.227681",
        "extracted_at_epoch": 1747376952,
        "extraction_url": "https://medium.com/tag/apache-airflow/archive",
        "tag": "apache-airflow"
    },
    {
        "author_name": "Indrasena Manga",
        "author_url": "https://medium.com/@indrasenamanga",
        "published_at": "2025-05-03 03:17:19.136000",
        "reading_time_minutes": 2.158490566037736,
        "story_url": "https://medium.com/@indrasenamanga/ethical-dags-should-your-dag-know-whats-right-and-what-s-wrong-ac4515786b35",
        "subtitle": "What if your Airflow DAGs paused not just on technical failure but when something feels wrong?",
        "title": "Ethical DAGs: Should Your DAG know what’s right and what’s wrong??",
        "extraction_id": "c5c44132-ea9e-4585-adc0-ec835716aaac",
        "extracted_at": "2025-05-16 06:29:12.227681",
        "extracted_at_epoch": 1747376952,
        "extraction_url": "https://medium.com/tag/apache-airflow/archive",
        "tag": "apache-airflow"
    },
    {
        "author_name": "Vijay Gadhave",
        "author_url": "https://medium.com/@vijaygadhave2014",
        "published_at": "2025-04-14 11:24:34.885000",
        "reading_time_minutes": 3.6037735849056607,
        "story_url": "https://medium.com/@vijaygadhave2014/branching-out-master-conditional-logic-in-your-data-pipelines-41a811c1a028",
        "subtitle": "Note: If you’re not a medium member, CLICK HERE",
        "title": "Branching Out: Master Conditional Logic in Your Data Pipelines",
        "extraction_id": "c5c44132-ea9e-4585-adc0-ec835716aaac",
        "extracted_at": "2025-05-16 06:29:12.227681",
        "extracted_at_epoch": 1747376952,
        "extraction_url": "https://medium.com/tag/apache-airflow/archive",
        "tag": "apache-airflow"
    },
    {
        "author_name": "Akhilsharmanittala",
        "author_url": "https://medium.com/@akhilsharmanittala",
        "published_at": "2025-04-21 11:48:05.317000",
        "reading_time_minutes": 6.659748427672955,
        "story_url": "https://medium.com/@akhilsharmanittala/getting-started-with-apache-airflow-a-guide-to-workflow-automation-67a7206ad6f1",
        "subtitle": "In today’s data-driven world, managing complex workflows has become a crucial part of building scalable and reliable systems. Whether…",
        "title": "🔧 Getting Started with Apache Airflow: A Guide to Workflow Automation",
        "extraction_id": "c5c44132-ea9e-4585-adc0-ec835716aaac",
        "extracted_at": "2025-05-16 06:29:12.227681",
        "extracted_at_epoch": 1747376952,
        "extraction_url": "https://medium.com/tag/apache-airflow/archive",
        "tag": "apache-airflow"
    },
    {
        "author_name": "CortexFlow",
        "author_url": "https://medium.com/@lorenzobradanini964",
        "published_at": "2025-04-16 13:41:23.179000",
        "reading_time_minutes": 9.481446540880503,
        "story_url": "https://medium.com/the-software-frontier/mastering-apache-airflow-orchestrating-scalable-and-efficient-data-workflows-4baf1560936d",
        "subtitle": "A Somewhat Comprehensive Guide to Task Management, Operators, and Advanced Features in Airflow",
        "title": "Mastering Apache Airflow: Orchestrating Scalable and Efficient Data Workflows",
        "extraction_id": "c5c44132-ea9e-4585-adc0-ec835716aaac",
        "extracted_at": "2025-05-16 06:29:12.227681",
        "extracted_at_epoch": 1747376952,
        "extraction_url": "https://medium.com/tag/apache-airflow/archive",
        "tag": "apache-airflow"
    },
    {
        "author_name": "Karlmarx Karunanithi",
        "author_url": "https://medium.com/@karlmarxkarunanithi",
        "published_at": "2025-04-22 22:51:12.444000",
        "reading_time_minutes": 3.4216981132075475,
        "story_url": "https://medium.com/cloud-native-chronicles/orchestrating-the-chaos-building-scalable-data-pipelines-a-dive-into-dags-airflow-and-mwaa-eff969fff013",
        "subtitle": "“Orchestrate Everything: Build Smarter Pipelines at Scale”",
        "title": "Orchestrating the Chaos: Building Scalable Data Pipelines —  A Dive into DAGs, Airflow, and MWAA",
        "extraction_id": "c5c44132-ea9e-4585-adc0-ec835716aaac",
        "extracted_at": "2025-05-16 06:29:12.227681",
        "extracted_at_epoch": 1747376952,
        "extraction_url": "https://medium.com/tag/apache-airflow/archive",
        "tag": "apache-airflow"
    },
    {
        "author_name": "Rajveer Singh",
        "author_url": "https://medium.com/@veermarwaha03",
        "published_at": "2025-05-04 13:44:09.899000",
        "reading_time_minutes": 3.9201257861635224,
        "story_url": "https://medium.com/@veermarwaha03/lightweight-workflows-with-golang-and-airflow-8eab5c0a7093",
        "subtitle": "Apache Airflow is a powerful open-source platform for workflow orchestration. Trusted by tech giants like Adobe, Airbnb, Slack, and…",
        "title": "Lightweight Workflows with GoLang and Airflow",
        "extraction_id": "c5c44132-ea9e-4585-adc0-ec835716aaac",
        "extracted_at": "2025-05-16 06:29:12.227681",
        "extracted_at_epoch": 1747376952,
        "extraction_url": "https://medium.com/tag/apache-airflow/archive",
        "tag": "apache-airflow"
    }
]