[
    {
        "author_name": "Mahdi Karabiben",
        "author_url": "https://towardsdatascience.com/@mahdiqb",
        "extracted_at": "2023-05-26 09:11:48.057242",
        "extracted_at_epoch": 1685092308,
        "extraction_id": "449018cd-25b1-47a7-bf9a-037d2347bdc9",
        "extraction_url": "https://medium.com/tag/dbt/archive/2023/05/22",
        "published_at": "2023-05-22T14:41:24.746Z",
        "reading_time_minutes": 8,
        "story_url": "https://towardsdatascience.com/writing-design-docs-for-data-pipelines-d49550f95580",
        "subtitle": "Exploring the what, why, and how of design docs for data…",
        "tag": "dbt",
        "title": "Writing design docs for data pipelines"
    },
    {
        "author_name": "Thirahealth",
        "author_url": "https://medium.com/@thirahealth12023",
        "extracted_at": "2023-05-26 09:11:48.057242",
        "extracted_at_epoch": 1685092308,
        "extraction_id": "449018cd-25b1-47a7-bf9a-037d2347bdc9",
        "extraction_url": "https://medium.com/tag/dbt/archive/2023/05/22",
        "published_at": "2023-05-22T06:39:50.388Z",
        "reading_time_minutes": 1,
        "story_url": "https://medium.com/@thirahealth12023/dialectical-behavior-therapy-and-its-role-in-treating-depression-filesfm-cdc386deb469",
        "subtitle": "-",
        "tag": "dbt",
        "title": "Dialectical Behavior Therapy and Its Role in Treating Depression — Filesfm"
    },
    {
        "author_name": "Joey Holmesmeyer",
        "author_url": "https://blog.startupstash.com/@joey_30056",
        "extracted_at": "2023-05-26 09:11:48.057242",
        "extracted_at_epoch": 1685092308,
        "extraction_id": "449018cd-25b1-47a7-bf9a-037d2347bdc9",
        "extraction_url": "https://medium.com/tag/dbt/archive/2023/05/22",
        "published_at": "2023-05-22T23:29:09.079Z",
        "reading_time_minutes": 4,
        "story_url": "https://blog.startupstash.com/mastering-your-data-landscape-with-dbt-labs-a-game-changer-for-small-businesses-207ace176f2b",
        "subtitle": "-",
        "tag": "dbt",
        "title": "Mastering Your Data Landscape With DBT Labs: A Game-Changer For Small Businesses"
    },
    {
        "author_name": "Dave Flynn",
        "author_url": "https://medium.com/@daveflynn",
        "extracted_at": "2023-05-26 09:11:48.057242",
        "extracted_at_epoch": 1685092308,
        "extraction_id": "449018cd-25b1-47a7-bf9a-037d2347bdc9",
        "extraction_url": "https://medium.com/tag/dbt/archive/2023/05/18",
        "published_at": "2023-05-18T18:46:37.769Z",
        "reading_time_minutes": 3,
        "story_url": "https://medium.com/inthepipeline/zero-config-code-review-and-data-profiling-tool-for-dbt-projects-8b6de40964b4",
        "subtitle": "-",
        "tag": "dbt",
        "title": "Zero config code review and data profiling tool for dbt projects"
    },
    {
        "author_name": "Tabular",
        "author_url": "https://medium.com/@tabular",
        "extracted_at": "2023-05-26 09:11:48.057242",
        "extracted_at_epoch": 1685092308,
        "extraction_id": "449018cd-25b1-47a7-bf9a-037d2347bdc9",
        "extraction_url": "https://medium.com/tag/dbt/archive/2023/05/19",
        "published_at": "2023-05-19T19:06:48.531Z",
        "reading_time_minutes": 5,
        "story_url": "https://www.linkedin.com/in/fokkodriesprong/",
        "subtitle": "-",
        "tag": "dbt",
        "title": "Using dbt with Tabular"
    },
    {
        "author_name": "Thirahealth",
        "author_url": "https://medium.com/@thirahealth12023",
        "extracted_at": "2023-05-26 09:11:48.057242",
        "extracted_at_epoch": 1685092308,
        "extraction_id": "449018cd-25b1-47a7-bf9a-037d2347bdc9",
        "extraction_url": "https://medium.com/tag/dbt/archive/2023/05/24",
        "published_at": "2023-05-24T00:29:40.515Z",
        "reading_time_minutes": 1,
        "story_url": "https://medium.com/@thirahealth12023/how-to-use-affirmations-with-dbts-stop-skill-for-anxiety-relief-weebly-6a01cace5d55",
        "subtitle": "-",
        "tag": "dbt",
        "title": "How to use Affirmations with DBT’s STOP Skill for Anxiety Relief — Weebly"
    },
    {
        "author_name": "Maroof Ashraf",
        "author_url": "https://medium.com/@maroofashraf987",
        "extracted_at": "2023-05-26 09:11:48.057242",
        "extracted_at_epoch": 1685092308,
        "extraction_id": "449018cd-25b1-47a7-bf9a-037d2347bdc9",
        "extraction_url": "https://medium.com/tag/dbt/archive/2023/05/23",
        "published_at": "2023-05-23T14:13:25.723Z",
        "reading_time_minutes": 2,
        "story_url": "https://medium.com/@maroofashraf987/master-the-data-alchemy-3ff57a25b89e",
        "subtitle": "-",
        "tag": "dbt",
        "title": "🔮 Master the Data Alchemy"
    },
    {
        "author_name": "Step into Yourself",
        "author_url": "https://medium.com/@stepinto-yourself",
        "extracted_at": "2023-05-26 09:11:48.057242",
        "extracted_at_epoch": 1685092308,
        "extraction_id": "449018cd-25b1-47a7-bf9a-037d2347bdc9",
        "extraction_url": "https://medium.com/tag/dbt/archive/2023/05/22",
        "published_at": "2023-05-22T12:12:51.041Z",
        "reading_time_minutes": 1,
        "story_url": "https://www.stepinto-yourself.com/what-is-dialectical-behavioural-therapy",
        "subtitle": "-",
        "tag": "dbt",
        "title": "WHAT IS DBT? — Stepinto-Yourself"
    },
    {
        "author_name": "Thirahealth",
        "author_url": "https://medium.com/@thirahealth12023",
        "extracted_at": "2023-05-26 09:11:48.057242",
        "extracted_at_epoch": 1685092308,
        "extraction_id": "449018cd-25b1-47a7-bf9a-037d2347bdc9",
        "extraction_url": "https://medium.com/tag/dbt/archive/2023/05/18",
        "published_at": "2023-05-18T02:41:12.723Z",
        "reading_time_minutes": 1,
        "story_url": "https://goo.gl/maps/NTouVi4SWZi9YUrg9",
        "subtitle": "-",
        "tag": "dbt",
        "title": "Effective Treatment Options for Anxiety and Depression at THIRA Health — Filesfm"
    },
    {
        "author_name": "Mahdi Karabiben",
        "author_url": "https://zendesk.engineering/@mahdiqb",
        "extracted_at": "2023-05-26 09:11:48.057242",
        "extracted_at_epoch": 1685092308,
        "extraction_id": "449018cd-25b1-47a7-bf9a-037d2347bdc9",
        "extraction_url": "https://medium.com/tag/dbt/archive/2023/05/23",
        "published_at": "2023-05-23T04:47:57.496Z",
        "reading_time_minutes": 10,
        "story_url": "https://zendesk.engineering/dbt-at-zendesk-part-i-setting-foundations-for-scalability-34b55e6a6aa1",
        "subtitle": "-",
        "tag": "dbt",
        "title": "dbt at Zendesk — Part I: Setting foundations for scalability"
    },
    {
        "author_name": "Thirahealth",
        "author_url": "https://medium.com/@thirahealth12023",
        "extracted_at": "2023-05-26 09:11:48.057242",
        "extracted_at_epoch": 1685092308,
        "extraction_id": "449018cd-25b1-47a7-bf9a-037d2347bdc9",
        "extraction_url": "https://medium.com/tag/dbt/archive/2023/05/24",
        "published_at": "2023-05-24T00:27:19.174Z",
        "reading_time_minutes": 1,
        "story_url": "https://medium.com/@thirahealth12023/how-to-use-affirmations-with-dbts-stop-skill-for-anxiety-relief-wordpress-52dff536f3a9",
        "subtitle": "-",
        "tag": "dbt",
        "title": "How to use Affirmations with DBT’s STOP Skill for Anxiety Relief — WordPress"
    },
    {
        "author_name": "Thirahealth",
        "author_url": "https://medium.com/@thirahealth12023",
        "extracted_at": "2023-05-26 09:11:48.057242",
        "extracted_at_epoch": 1685092308,
        "extraction_id": "449018cd-25b1-47a7-bf9a-037d2347bdc9",
        "extraction_url": "https://medium.com/tag/dbt/archive/2023/05/23",
        "published_at": "2023-05-23T07:08:52.537Z",
        "reading_time_minutes": 2,
        "story_url": "https://medium.com/@thirahealth12023/dialectical-behavior-therapy-and-its-role-in-treating-depression-slideshare-ed267ecc2874",
        "subtitle": "-",
        "tag": "dbt",
        "title": "Dialectical Behavior Therapy and Its Role in Treating Depression — Slideshare"
    },
    {
        "author_name": "Venkatakrishnan",
        "author_url": "https://medium.com/@venkatkarthick15",
        "extracted_at": "2023-05-26 09:11:48.057242",
        "extracted_at_epoch": 1685092308,
        "extraction_id": "449018cd-25b1-47a7-bf9a-037d2347bdc9",
        "extraction_url": "https://medium.com/tag/dbt/archive/2023/05/19",
        "published_at": "2023-05-19T08:06:01.128Z",
        "reading_time_minutes": 7,
        "story_url": "https://medium.com/@venkatkarthick15/unleashing-the-power-of-dbt-snowflake-for-data-pipelining-a-netflix-use-case-b68c960cc557",
        "subtitle": "-",
        "tag": "dbt",
        "title": "Unleashing the Power of DBT-Snowflake for Data Pipelining: A Netflix Use Case"
    },
    {
        "author_name": "Ashley Gangl",
        "author_url": "https://medium.com/@ashley_64727",
        "extracted_at": "2023-05-26 09:11:48.057242",
        "extracted_at_epoch": 1685092308,
        "extraction_id": "449018cd-25b1-47a7-bf9a-037d2347bdc9",
        "extraction_url": "https://medium.com/tag/dbt/archive/2023/05/23",
        "published_at": "2023-05-23T13:35:51.951Z",
        "reading_time_minutes": 4,
        "story_url": "https://medium.com/neurospice/i-should-be-more-attentive-452800686392",
        "subtitle": "-",
        "tag": "dbt",
        "title": "“Mom guilt” I Should Be More…"
    },
    {
        "author_name": "Taylor Brownlow",
        "author_url": "https://medium.com/@taylor-count",
        "extracted_at": "2023-05-26 09:11:48.057242",
        "extracted_at_epoch": 1685092308,
        "extraction_id": "449018cd-25b1-47a7-bf9a-037d2347bdc9",
        "extraction_url": "https://medium.com/tag/dbt/archive/2023/05/18",
        "published_at": "2023-05-18T15:39:23.006Z",
        "reading_time_minutes": 5,
        "story_url": "https://medium.com/@taylor-count/count-dbt-making-your-data-models-radically-transparent-8919a6f2ddbf",
        "subtitle": "-",
        "tag": "dbt",
        "title": "Count + dbt: Making your data models radically transparent"
    },
    {
        "author_name": "Claudio Manoel da Silva e Sousa Neto",
        "author_url": "https://medium.com/@claudiomanoel2006",
        "extracted_at": "2023-05-26 09:11:48.057242",
        "extracted_at_epoch": 1685092308,
        "extraction_id": "449018cd-25b1-47a7-bf9a-037d2347bdc9",
        "extraction_url": "https://medium.com/tag/dbt/archive/2023/05/22",
        "published_at": "2023-05-22T14:42:52.540Z",
        "reading_time_minutes": 6,
        "story_url": "https://medium.com/localizalabs/monitoramento-de-utiliza%C3%A7%C3%A3o-das-camadas-do-data-lake-no-contexto-de-self-service-bi-na-localiza-5d3fe0d227ab",
        "subtitle": "-",
        "tag": "dbt",
        "title": "Monitoramento de Utilização das Camadas do Data Lake no contexto de Self-Service BI na Localiza"
    },
    {
        "author_name": "Thirahealth",
        "author_url": "https://medium.com/@thirahealth12023",
        "extracted_at": "2023-05-26 09:11:48.057242",
        "extracted_at_epoch": 1685092308,
        "extraction_id": "449018cd-25b1-47a7-bf9a-037d2347bdc9",
        "extraction_url": "https://medium.com/tag/dbt/archive/2023/05/23",
        "published_at": "2023-05-23T01:21:03.866Z",
        "reading_time_minutes": 1,
        "story_url": "https://medium.com/@thirahealth12023/how-to-use-affirmations-with-dbts-stop-skill-for-anxiety-relief-blogspot-85b086fc25bd",
        "subtitle": "-",
        "tag": "dbt",
        "title": "How to use Affirmations with DBT’s STOP Skill for Anxiety Relief — Blogspot"
    },
    {
        "author_name": "Thirahealth",
        "author_url": "https://medium.com/@thirahealth12023",
        "extracted_at": "2023-05-26 09:11:48.057242",
        "extracted_at_epoch": 1685092308,
        "extraction_id": "449018cd-25b1-47a7-bf9a-037d2347bdc9",
        "extraction_url": "https://medium.com/tag/dbt/archive/2023/05/22",
        "published_at": "2023-05-22T06:43:28.419Z",
        "reading_time_minutes": 2,
        "story_url": "https://medium.com/@thirahealth12023/dialectical-behavior-therapy-and-its-role-in-treating-depression-dochub-7c214d6797eb",
        "subtitle": "-",
        "tag": "dbt",
        "title": "Dialectical Behavior Therapy and Its Role in Treating Depression — Dochub"
    },
    {
        "author_name": "Paddy Alton",
        "author_url": "https://medium.com/@paddyalton",
        "extracted_at": "2023-05-26 09:11:48.057242",
        "extracted_at_epoch": 1685092308,
        "extraction_id": "449018cd-25b1-47a7-bf9a-037d2347bdc9",
        "extraction_url": "https://medium.com/tag/dbt/archive/2023/05/22",
        "published_at": "2023-05-22T12:16:27.859Z",
        "reading_time_minutes": 5,
        "story_url": "https://medium.com/apolitical-engineering/how-we-use-dbt-and-bigquery-external-connections-to-easily-and-reliably-warehouse-cloud-sql-data-b0f68e873aad",
        "subtitle": "-",
        "tag": "dbt",
        "title": "How we use DBT and BigQuery External Connections to easily and reliably warehouse Cloud SQL data"
    },
    {
        "author_name": "Thirahealth",
        "author_url": "https://medium.com/@thirahealth12023",
        "extracted_at": "2023-05-26 09:11:48.057242",
        "extracted_at_epoch": 1685092308,
        "extraction_id": "449018cd-25b1-47a7-bf9a-037d2347bdc9",
        "extraction_url": "https://medium.com/tag/dbt/archive/2023/05/24",
        "published_at": "2023-05-24T06:58:59.109Z",
        "reading_time_minutes": 1,
        "story_url": "https://medium.com/@thirahealth12023/how-to-use-affirmations-with-dbts-stop-skill-for-anxiety-relief-59282eeae90e",
        "subtitle": "-",
        "tag": "dbt",
        "title": "How to use Affirmations with DBT’s STOP Skill for Anxiety Relief — Tumblr"
    },
    {
        "author_name": "Yoav Nordmann",
        "author_url": "https://medium.com/@yoav.nordmann",
        "extracted_at": "2023-05-26 09:11:48.057242",
        "extracted_at_epoch": 1685092308,
        "extraction_id": "449018cd-25b1-47a7-bf9a-037d2347bdc9",
        "extraction_url": "https://medium.com/tag/dbt/archive/2023/05/23",
        "published_at": "2023-05-23T07:02:02.313Z",
        "reading_time_minutes": 6,
        "story_url": "https://medium.com/everything-full-stack/dismantling-bigdata-with-duckdb-1c39ca3970c5",
        "subtitle": "What if I told you, you can run Big Data Analysis and ETLs from the…",
        "tag": "dbt",
        "title": "Dismantling BigData with DuckDB"
    },
    {
        "author_name": "Thirahealth",
        "author_url": "https://medium.com/@thirahealth12023",
        "extracted_at": "2023-05-26 09:11:48.057242",
        "extracted_at_epoch": 1685092308,
        "extraction_id": "449018cd-25b1-47a7-bf9a-037d2347bdc9",
        "extraction_url": "https://medium.com/tag/dbt/archive/2023/05/23",
        "published_at": "2023-05-23T00:57:56.849Z",
        "reading_time_minutes": 2,
        "story_url": "https://medium.com/@thirahealth12023/how-to-use-affirmations-with-dbts-stop-skill-for-anxiety-relief-google-42063272e73e",
        "subtitle": "-",
        "tag": "dbt",
        "title": "How to use Affirmations with DBT’s STOP Skill for Anxiety Relief — Google"
    },
    {
        "author_name": "Thirahealth",
        "author_url": "https://medium.com/@thirahealth12023",
        "extracted_at": "2023-05-26 09:11:48.057242",
        "extracted_at_epoch": 1685092308,
        "extraction_id": "449018cd-25b1-47a7-bf9a-037d2347bdc9",
        "extraction_url": "https://medium.com/tag/dbt/archive/2023/05/18",
        "published_at": "2023-05-18T02:43:19.356Z",
        "reading_time_minutes": 2,
        "story_url": "https://goo.gl/maps/NTouVi4SWZi9YUrg9",
        "subtitle": "-",
        "tag": "dbt",
        "title": "Effective Treatment Options for Anxiety and Depression at THIRA Health — Dochub"
    },
    {
        "author_name": "Thirahealth",
        "author_url": "https://medium.com/@thirahealth12023",
        "extracted_at": "2023-05-26 09:11:48.057242",
        "extracted_at_epoch": 1685092308,
        "extraction_id": "449018cd-25b1-47a7-bf9a-037d2347bdc9",
        "extraction_url": "https://medium.com/tag/dbt/archive/2023/05/18",
        "published_at": "2023-05-18T03:07:12.460Z",
        "reading_time_minutes": 2,
        "story_url": "https://medium.com/@thirahealth12023/dialectical-behavior-therapy-and-its-role-in-treating-depression-sendspace-95fcf717962a",
        "subtitle": "-",
        "tag": "dbt",
        "title": "Dialectical Behavior Therapy and Its Role in Treating Depression — Sendspace"
    },
    {
        "author_name": "Thirahealth",
        "author_url": "https://medium.com/@thirahealth12023",
        "extracted_at": "2023-05-26 09:11:48.057242",
        "extracted_at_epoch": 1685092308,
        "extraction_id": "449018cd-25b1-47a7-bf9a-037d2347bdc9",
        "extraction_url": "https://medium.com/tag/dbt/archive/2023/05/19",
        "published_at": "2023-05-19T00:59:50.084Z",
        "reading_time_minutes": 1,
        "story_url": "https://goo.gl/maps/NTouVi4SWZi9YUrg9",
        "subtitle": "-",
        "tag": "dbt",
        "title": "Effective Treatment Options for Anxiety and Depression at THIRA Health — Slideshare"
    },
    {
        "author_name": "Step into Yourself",
        "author_url": "https://medium.com/@stepinto-yourself",
        "extracted_at": "2023-05-26 09:11:48.057242",
        "extracted_at_epoch": 1685092308,
        "extraction_id": "449018cd-25b1-47a7-bf9a-037d2347bdc9",
        "extraction_url": "https://medium.com/tag/dbt/archive/2023/05/22",
        "published_at": "2023-05-22T12:15:41.613Z",
        "reading_time_minutes": 1,
        "story_url": "https://medium.com/@stepinto-yourself/online-mental-health-service-specialising-stepinto-yourself-f23097e5acca",
        "subtitle": "-",
        "tag": "dbt",
        "title": "Online Mental Health Service Specialising — Stepinto-Yourself,"
    },
    {
        "author_name": "DataGeeks",
        "author_url": "https://medium.com/@datageeks",
        "extracted_at": "2023-05-26 09:11:48.057242",
        "extracted_at_epoch": 1685092308,
        "extraction_id": "449018cd-25b1-47a7-bf9a-037d2347bdc9",
        "extraction_url": "https://medium.com/tag/dbt/archive/2023/05/22",
        "published_at": "2023-05-22T18:08:06.939Z",
        "reading_time_minutes": 4,
        "story_url": "https://medium.com/@datageeks/start-your-journey-with-dbt-core-and-snowflake-b6ec673c6b26",
        "subtitle": "-",
        "tag": "dbt",
        "title": "Start your journey with DBT Core and Snowflake."
    },
    {
        "author_name": "Thirahealth",
        "author_url": "https://medium.com/@thirahealth12023",
        "extracted_at": "2023-05-26 09:11:48.057242",
        "extracted_at_epoch": 1685092308,
        "extraction_id": "449018cd-25b1-47a7-bf9a-037d2347bdc9",
        "extraction_url": "https://medium.com/tag/dbt/archive/2023/05/18",
        "published_at": "2023-05-18T03:05:13.766Z",
        "reading_time_minutes": 2,
        "story_url": "https://medium.com/@thirahealth12023/dialectical-behavior-therapy-and-its-role-in-treating-depression-edoc-459148662963",
        "subtitle": "-",
        "tag": "dbt",
        "title": "Dialectical Behavior Therapy and Its Role in Treating Depression — Edocr"
    },
    {
        "author_name": "Thirahealth",
        "author_url": "https://medium.com/@thirahealth12023",
        "extracted_at": "2023-05-26 09:11:48.057242",
        "extracted_at_epoch": 1685092308,
        "extraction_id": "449018cd-25b1-47a7-bf9a-037d2347bdc9",
        "extraction_url": "https://medium.com/tag/dbt/archive/2023/05/19",
        "published_at": "2023-05-19T01:01:57.067Z",
        "reading_time_minutes": 1,
        "story_url": "https://goo.gl/maps/NTouVi4SWZi9YUrg9",
        "subtitle": "-",
        "tag": "dbt",
        "title": "Effective Treatment Options for Anxiety and Depression at THIRA Health — Mediafire"
    },
    {
        "author_name": "Thirahealth",
        "author_url": "https://medium.com/@thirahealth12023",
        "extracted_at": "2023-05-26 09:11:48.057242",
        "extracted_at_epoch": 1685092308,
        "extraction_id": "449018cd-25b1-47a7-bf9a-037d2347bdc9",
        "extraction_url": "https://medium.com/tag/dbt/archive/2023/05/23",
        "published_at": "2023-05-23T07:10:34.329Z",
        "reading_time_minutes": 2,
        "story_url": "https://medium.com/@thirahealth12023/dialectical-behavior-therapy-and-its-role-in-treating-depression-mediafire-79f0e4a8672b",
        "subtitle": "-",
        "tag": "dbt",
        "title": "Dialectical Behavior Therapy and Its Role in Treating Depression — Mediafire"
    },
    {
        "author_name": "Дмитрий ПереводIT",
        "author_url": "https://medium.com/@svobodavsem",
        "extracted_at": "2023-05-26 09:11:48.057242",
        "extracted_at_epoch": 1685092308,
        "extraction_id": "449018cd-25b1-47a7-bf9a-037d2347bdc9",
        "extraction_url": "https://medium.com/tag/dbt/archive/2023/05/18",
        "published_at": "2023-05-18T16:02:19.545Z",
        "reading_time_minutes": 4,
        "story_url": "https://medium.com/nuances-of-programming/%D0%BF%D0%BB%D0%B0%D0%BD%D0%B8%D1%80%D0%BE%D0%B2%D0%B0%D0%BD%D0%B8%D0%B5-%D0%B8-%D0%BE%D1%80%D0%BA%D0%B5%D1%81%D1%82%D1%80%D0%B0%D1%86%D0%B8%D1%8F-%D0%BE%D0%B1%D0%BB%D0%B0%D1%87%D0%BD%D1%8B%D1%85-%D0%B7%D0%B0%D0%B4%D0%B0%D1%87-dbt-cloud-%D1%81-%D0%BF%D0%BE%D0%BC%D0%BE%D1%89%D1%8C%D1%8E-prefect-d31fde3998d8",
        "subtitle": "-",
        "tag": "dbt",
        "title": "Планирование и оркестрация облачных задач dbt Cloud с помощью Prefect"
    }
]