[
    {
        "author_name": "Giorgos Myrianthous",
        "author_url": "https://medium.com/@gmyrianthous",
        "published_at": "2024-04-16 10:23:25.985000",
        "reading_time_minutes": 11.571698113207548,
        "story_url": "https://medium.com/plum-fintech/dbt-airflow-50b2c93f91cc",
        "subtitle": "Building dbt-airflow: A Python package that integrates dbt and Airflow",
        "title": "dbt + Airflow = ❤",
        "extraction_id": "70ed0cc7-918b-48f7-814b-236eb1e11b03",
        "extracted_at": "2024-04-26 06:34:11.429141",
        "extracted_at_epoch": 1714113251,
        "extraction_url": "https://medium.com/tag/dbt/archive",
        "tag": "dbt"
    },
    {
        "author_name": "Lee Doolan",
        "author_url": "https://medium.com/@leedoolan77",
        "published_at": "2024-04-22 15:09:07.787000",
        "reading_time_minutes": 8.757547169811321,
        "story_url": "https://medium.com/cts-technologies/stop-scheming-start-streaming-bb33c228a368",
        "subtitle": "The Power of BigQuery Event Stream Tables",
        "title": "Stop Scheming, Start Streaming",
        "extraction_id": "70ed0cc7-918b-48f7-814b-236eb1e11b03",
        "extracted_at": "2024-04-26 06:34:11.429141",
        "extracted_at_epoch": 1714113251,
        "extraction_url": "https://medium.com/tag/dbt/archive",
        "tag": "dbt"
    },
    {
        "author_name": "Yusuf Gözübüyük",
        "author_url": "https://medium.com/@yusufgzbyk",
        "published_at": "2024-04-24 13:53:36.250000",
        "reading_time_minutes": 3.6141509433962264,
        "story_url": "https://medium.com/i%CC%87stanbuldatascienceacademy/veri-analiti%C4%9Finde-modernle%C5%9Fme-dbt-veri-olu%C5%9Fturma-arac%C4%B1-1bb218a82d3a",
        "subtitle": "",
        "title": "Veri Analitiğinde Modernleşme: dbt Veri Oluşturma Aracı",
        "extraction_id": "70ed0cc7-918b-48f7-814b-236eb1e11b03",
        "extracted_at": "2024-04-26 06:34:11.429141",
        "extracted_at_epoch": 1714113251,
        "extraction_url": "https://medium.com/tag/dbt/archive",
        "tag": "dbt"
    },
    {
        "author_name": "Dominik Jagoda",
        "author_url": "https://medium.com/@dominik.jagoda881",
        "published_at": "2024-04-21 21:10:19.499000",
        "reading_time_minutes": 2.5622641509433963,
        "story_url": "https://medium.com/@dominik.jagoda881/dbt-compilation-error-none-has-no-attribute-table-fc5fe3e3ef33",
        "subtitle": "Execute, or not execute, that is the question. In the following article, I have decided to explain a solution to a problem often…",
        "title": "dbt Compilation Error: ‘None’ has no attribute ‘table’",
        "extraction_id": "70ed0cc7-918b-48f7-814b-236eb1e11b03",
        "extracted_at": "2024-04-26 06:34:11.429141",
        "extracted_at_epoch": 1714113251,
        "extraction_url": "https://medium.com/tag/dbt/archive",
        "tag": "dbt"
    },
    {
        "author_name": "Andrea Bombino",
        "author_url": "https://medium.com/@andrea.bombino94",
        "published_at": "2024-04-23 09:13:28.328000",
        "reading_time_minutes": 3.804716981132075,
        "story_url": "https://medium.astrafy.io/refactor-your-way-to-sucess-a-practical-guide-to-dbt-core-code-optimization-1929144aca91",
        "subtitle": "As all Data Engineers know, sometimes you need to move fast and get things done quickly. While this “quick and dirty” approach might be…",
        "title": "Refactor your way to Success: A practical guide to dbt Core code Optimization",
        "extraction_id": "70ed0cc7-918b-48f7-814b-236eb1e11b03",
        "extracted_at": "2024-04-26 06:34:11.429141",
        "extracted_at_epoch": 1714113251,
        "extraction_url": "https://medium.com/tag/dbt/archive",
        "tag": "dbt"
    },
    {
        "author_name": "Suneet Sahadevan",
        "author_url": "https://medium.com/@suneetsahadevan",
        "published_at": "2024-04-19 08:22:41.782000",
        "reading_time_minutes": 0.5773584905660377,
        "story_url": "https://medium.com/@suneetsahadevan/read-csv-or-excel-files-into-snowflake-using-python-dbt-models-3483f6818a2b",
        "subtitle": "I searched a lot of forums for a python model in DBT which can read csv or excel files into a dataframe but I couldn't find it.",
        "title": "Read CSV or Excel files into Snowflake using Python DBT Models",
        "extraction_id": "70ed0cc7-918b-48f7-814b-236eb1e11b03",
        "extracted_at": "2024-04-26 06:34:11.429141",
        "extracted_at_epoch": 1714113251,
        "extraction_url": "https://medium.com/tag/dbt/archive",
        "tag": "dbt"
    },
    {
        "author_name": "Kurnivan Noer Yusvianto",
        "author_url": "https://medium.com/@kurnivannoery",
        "published_at": "2024-04-18 10:04:09.107000",
        "reading_time_minutes": 8.79559748427673,
        "story_url": "https://towardsdev.com/enhancing-data-transformation-with-dbt-and-snowflake-5f62c1fa2392",
        "subtitle": "Data transformation is manipulating raw data into enriched data before or after loading it into a data warehouse. This prepares the data…",
        "title": "Enhancing Data Transformation with dbt and Snowflake",
        "extraction_id": "70ed0cc7-918b-48f7-814b-236eb1e11b03",
        "extracted_at": "2024-04-26 06:34:11.429141",
        "extracted_at_epoch": 1714113251,
        "extraction_url": "https://medium.com/tag/dbt/archive",
        "tag": "dbt"
    },
    {
        "author_name": "Dave Flynn",
        "author_url": "https://medium.com/@daveflynn",
        "published_at": "2024-04-18 10:33:10.062000",
        "reading_time_minutes": 4.316352201257861,
        "story_url": "https://medium.com/inthepipeline/so-you-think-youve-got-dbt-test-bloat-37491fb330d5",
        "subtitle": "After a certain threshold, alert fatigue becomes an issue, especially when upstream issues trigger hundreds of downstream alerts",
        "title": "So, you think you’ve got dbt test bloat?",
        "extraction_id": "70ed0cc7-918b-48f7-814b-236eb1e11b03",
        "extracted_at": "2024-04-26 06:34:11.429141",
        "extracted_at_epoch": 1714113251,
        "extraction_url": "https://medium.com/tag/dbt/archive",
        "tag": "dbt"
    },
    {
        "author_name": "Tennis",
        "author_url": "https://medium.com/@tennis_40356",
        "published_at": "2024-04-20 17:57:01.929000",
        "reading_time_minutes": 0.26037735849056604,
        "story_url": "https://medium.com/@tennis_40356/money-fine-loan-app-customer-care-number8319053360-8319053360-call-me-c09838139d66",
        "subtitle": "",
        "title": "Money Fine loan app customer care number’8319053360/+!8319053360’//call me",
        "extraction_id": "70ed0cc7-918b-48f7-814b-236eb1e11b03",
        "extracted_at": "2024-04-26 06:34:11.429141",
        "extracted_at_epoch": 1714113251,
        "extraction_url": "https://medium.com/tag/dbt/archive",
        "tag": "dbt"
    },
    {
        "author_name": "Sumit Bansal",
        "author_url": "https://medium.com/@sumitvp2007",
        "published_at": "2024-04-19 14:27:07.889000",
        "reading_time_minutes": 1.8830188679245283,
        "story_url": "https://medium.com/@sumitvp2007/master-emotional-wellness-top-dialectical-behaviour-therapy-dbt-courses-of-2024-478e3d029266",
        "subtitle": "Are you ready to transform your approach to emotional well-being? Dive into the world of Dialectical Behaviour Therapy (DBT) and unlock the…",
        "title": "Master Emotional Wellness: Top Dialectical Behaviour Therapy (DBT) Courses of 2024",
        "extraction_id": "70ed0cc7-918b-48f7-814b-236eb1e11b03",
        "extracted_at": "2024-04-26 06:34:11.429141",
        "extracted_at_epoch": 1714113251,
        "extraction_url": "https://medium.com/tag/dbt/archive",
        "tag": "dbt"
    },
    {
        "author_name": "Brenda Varguez",
        "author_url": "https://medium.com/@brendavarguez21",
        "published_at": "2024-04-18 20:06:23.006000",
        "reading_time_minutes": 5.919182389937108,
        "story_url": "https://awstip.com/coding-symphony-clickhouse-dbt-and-table-partitioning-order-by-and-primary-keys-part-3-16a25dd977ca",
        "subtitle": "This tutorial assumes that you have an existing dbt project configured to work with a ClickHouse instance. If you don’t, you can refer to…",
        "title": "Coding Symphony: ClickHouse + dbt and table partitioning, order by and primary keys (part 3)",
        "extraction_id": "70ed0cc7-918b-48f7-814b-236eb1e11b03",
        "extracted_at": "2024-04-26 06:34:11.429141",
        "extracted_at_epoch": 1714113251,
        "extraction_url": "https://medium.com/tag/dbt/archive",
        "tag": "dbt"
    },
    {
        "author_name": "Joshua",
        "author_url": "https://medium.com/@joshua881117",
        "published_at": "2024-04-26 08:38:46.489000",
        "reading_time_minutes": 16.96,
        "story_url": "https://medium.com/@joshua881117/%E5%9C%A8-dbt-%E4%B8%8A%E7%AE%A1%E7%90%86-bigquery-udf-205eb04cad76",
        "subtitle": "我是 Migo Data Engineer Team 的 Data Engineer Joshua，我們團隊使用 DBT 來進行數據 Transformation，且使用 Bigquery 作為資料倉儲，此篇文章是要介紹如何在 DBT 上管理 UDF。",
        "title": "在 DBT 上管理 Bigquery UDF",
        "extraction_id": "70ed0cc7-918b-48f7-814b-236eb1e11b03",
        "extracted_at": "2024-04-26 06:34:11.429141",
        "extracted_at_epoch": 1714113251,
        "extraction_url": "https://medium.com/tag/dbt/archive",
        "tag": "dbt"
    },
    {
        "author_name": "Matthieu Bonneviot",
        "author_url": "https://medium.com/@matthieu.bonneviot",
        "published_at": "2024-04-23 11:51:11.059000",
        "reading_time_minutes": 2.6814465408805033,
        "story_url": "https://medium.com/teads-engineering/dbt-unit-test-framework-72d9ca60c69b",
        "subtitle": "A dedicated framework for unit-testing has been released with dbt v1.8.0-b1, we gave it a try at Teads",
        "title": "dbt unit-test framework",
        "extraction_id": "70ed0cc7-918b-48f7-814b-236eb1e11b03",
        "extracted_at": "2024-04-26 06:34:11.429141",
        "extracted_at_epoch": 1714113251,
        "extraction_url": "https://medium.com/tag/dbt/archive",
        "tag": "dbt"
    },
    {
        "author_name": "DH",
        "author_url": "https://medium.com/@Benjamin0313",
        "published_at": "2024-04-21 14:51:32.329000",
        "reading_time_minutes": 1.4339622641509433,
        "story_url": "https://medium.com/@Benjamin0313/manage-dbt-documentation-using-dbt-osmosis-71674bf7395e",
        "subtitle": "When using dbt (data build tool), it’s indeed necessary to write YAML files, such as source files or model YAML files. These files serve as…",
        "title": "Manage dbt documentation using dbt-osmosis",
        "extraction_id": "70ed0cc7-918b-48f7-814b-236eb1e11b03",
        "extracted_at": "2024-04-26 06:34:11.429141",
        "extracted_at_epoch": 1714113251,
        "extraction_url": "https://medium.com/tag/dbt/archive",
        "tag": "dbt"
    },
    {
        "author_name": "Mark Rittman",
        "author_url": "https://medium.com/@markrittman",
        "published_at": "2024-04-25 13:06:03.167000",
        "reading_time_minutes": 5.483018867924528,
        "story_url": "https://blog.rittmananalytics.com/dynamic-data-model-definition-in-cube-using-python-and-jinja-9bc28f9d4cba",
        "subtitle": "At Rittman Analytics we’re big fans of Cube, pioneer of the “Headless BI” movement and used in many of our client projects including the…",
        "title": "Dynamic Data Model Definition in Cube using Python and Jinja",
        "extraction_id": "70ed0cc7-918b-48f7-814b-236eb1e11b03",
        "extracted_at": "2024-04-26 06:34:11.429141",
        "extracted_at_epoch": 1714113251,
        "extraction_url": "https://medium.com/tag/dbt/archive",
        "tag": "dbt"
    },
    {
        "author_name": "DH",
        "author_url": "https://medium.com/@Benjamin0313",
        "published_at": "2024-04-24 08:36:45.586000",
        "reading_time_minutes": 1.9056603773584906,
        "story_url": "https://medium.com/@Benjamin0313/using-dbt-to-create-a-star-chart-of-data-marts-and-sources-629eeffbc2a6",
        "subtitle": "dbt, by default, uses dbt docs to provide data lineage capabilities, which allows for the visualization of relationships between each…",
        "title": "Using dbt to create a star chart of data marts and sources",
        "extraction_id": "70ed0cc7-918b-48f7-814b-236eb1e11b03",
        "extracted_at": "2024-04-26 06:34:11.429141",
        "extracted_at_epoch": 1714113251,
        "extraction_url": "https://medium.com/tag/dbt/archive",
        "tag": "dbt"
    },
    {
        "author_name": "Sandun Dayananda",
        "author_url": "https://medium.com/@sandundayananda",
        "published_at": "2024-04-19 18:26:05.404000",
        "reading_time_minutes": 9.587735849056603,
        "story_url": "https://sandundayananda.medium.com/what-is-dbt-beginners-guide-ef3020caa2be",
        "subtitle": "A simple and full introduction to DBT",
        "title": "What is DBT — Beginners Guide",
        "extraction_id": "70ed0cc7-918b-48f7-814b-236eb1e11b03",
        "extracted_at": "2024-04-26 06:34:11.429141",
        "extracted_at_epoch": 1714113251,
        "extraction_url": "https://medium.com/tag/dbt/archive",
        "tag": "dbt"
    },
    {
        "author_name": "Will Davies",
        "author_url": "https://medium.com/@will_35759",
        "published_at": "2024-04-22 09:18:22.937000",
        "reading_time_minutes": 13.851886792452829,
        "story_url": "https://medium.com/orchestras-data-release-pipeline-blog/a-detailed-guide-to-running-dbt-core-in-production-in-aws-on-ecs-e89a644d2844",
        "subtitle": "How to run dbt Core as cheaply and reliably as possible on AWS",
        "title": "A detailed guide to running dbt Core in Production in AWS on ECS",
        "extraction_id": "70ed0cc7-918b-48f7-814b-236eb1e11b03",
        "extracted_at": "2024-04-26 06:34:11.429141",
        "extracted_at_epoch": 1714113251,
        "extraction_url": "https://medium.com/tag/dbt/archive",
        "tag": "dbt"
    },
    {
        "author_name": "Albert Franzi",
        "author_url": "https://medium.com/@FranziCros",
        "published_at": "2024-04-18 11:23:12.380000",
        "reading_time_minutes": 3.4103773584905657,
        "story_url": "https://medium.com/albert-franzi/democratizing-the-dbt-docs-and-the-elementary-quality-reports-2f11fed68d13",
        "subtitle": "In today’s fast-paced digital world, having immediate access to clear, accurate data documentation and quality reports isn’t just nice to…",
        "title": "Democratizing the DBT Docs and the Elementary Quality Reports",
        "extraction_id": "70ed0cc7-918b-48f7-814b-236eb1e11b03",
        "extracted_at": "2024-04-26 06:34:11.429141",
        "extracted_at_epoch": 1714113251,
        "extraction_url": "https://medium.com/tag/dbt/archive",
        "tag": "dbt"
    },
    {
        "author_name": "Krishna yogi",
        "author_url": "https://medium.com/@krishna-yogik",
        "published_at": "2024-04-19 21:30:24.381000",
        "reading_time_minutes": 8.464150943396225,
        "story_url": "https://krishna-yogik.medium.com/building-an-end-to-end-airflow-data-pipeline-with-bigquery-dbt-soda-bfca4e695f3b",
        "subtitle": "Dataset",
        "title": "Building an End-to-End Airflow Data Pipeline with BigQuery, dbt & Soda.",
        "extraction_id": "70ed0cc7-918b-48f7-814b-236eb1e11b03",
        "extracted_at": "2024-04-26 06:34:11.429141",
        "extracted_at_epoch": 1714113251,
        "extraction_url": "https://medium.com/tag/dbt/archive",
        "tag": "dbt"
    }
]