{
  "content": [
    {
      "content": null,
      "created": "2025-04-11T06:43:13.271909Z",
      "format": null,
      "hash": null,
      "hash_algorithm": null,
      "last_modified": "2025-04-11T06:42:59.876022Z",
      "mimetype": null,
      "name": "dim_medium_authors.parquet",
      "path": "dim_medium_authors.parquet",
      "size": 321359,
      "type": "file",
      "writable": true
    },
    {
      "content": null,
      "created": "2025-04-11T06:43:13.267909Z",
      "format": null,
      "hash": null,
      "hash_algorithm": null,
      "last_modified": "2025-04-11T06:42:59.384026Z",
      "mimetype": null,
      "name": "dim_dbt_repos.parquet",
      "path": "dim_dbt_repos.parquet",
      "size": 26981,
      "type": "file",
      "writable": true
    },
    {
      "content": null,
      "created": "2025-04-11T06:43:13.275909Z",
      "format": null,
      "hash": null,
      "hash_algorithm": null,
      "last_modified": "2025-04-11T06:43:11.303926Z",
      "mimetype": null,
      "name": "jupyter-lite.ipynb",
      "path": "jupyter-lite.ipynb",
      "size": 151902,
      "type": "notebook",
      "writable": true
    },
    {
      "content": null,
      "created": "2025-04-11T06:43:13.275909Z",
      "format": null,
      "hash": null,
      "hash_algorithm": null,
      "last_modified": "2025-04-11T06:42:59.432026Z",
      "mimetype": null,
      "name": "fct_medium_blogs_per_day.parquet",
      "path": "fct_medium_blogs_per_day.parquet",
      "size": 13217,
      "type": "file",
      "writable": true
    },
    {
      "content": null,
      "created": "2025-04-11T06:43:13.275909Z",
      "format": null,
      "hash": null,
      "hash_algorithm": null,
      "last_modified": "2025-04-11T06:42:59.940022Z",
      "mimetype": null,
      "name": "fct_medium_blogs.parquet",
      "path": "fct_medium_blogs.parquet",
      "size": 1033993,
      "type": "file",
      "writable": true
    },
    {
      "content": null,
      "created": "2025-04-11T06:43:13.275909Z",
      "format": null,
      "hash": null,
      "hash_algorithm": null,
      "last_modified": "2025-04-11T06:43:13.275909Z",
      "mimetype": null,
      "name": "reports",
      "path": "reports",
      "size": null,
      "type": "directory",
      "writable": true
    },
    {
      "content": null,
      "created": "2025-04-11T06:43:13.271909Z",
      "format": null,
      "hash": null,
      "hash_algorithm": null,
      "last_modified": "2025-04-11T06:43:02.248002Z",
      "mimetype": null,
      "name": "fct_dbt_interactors.parquet",
      "path": "fct_dbt_interactors.parquet",
      "size": 217492,
      "type": "file",
      "writable": true
    },
    {
      "content": null,
      "created": "2025-04-11T06:43:13.267909Z",
      "format": null,
      "hash": null,
      "hash_algorithm": null,
      "last_modified": "2025-04-11T06:42:59.364027Z",
      "mimetype": null,
      "name": "dim_dbt_discussions.parquet",
      "path": "dim_dbt_discussions.parquet",
      "size": 37498,
      "type": "file",
      "writable": true
    },
    {
      "content": null,
      "created": "2025-04-11T06:43:13.271909Z",
      "format": null,
      "hash": null,
      "hash_algorithm": null,
      "last_modified": "2025-04-11T06:43:00.624016Z",
      "mimetype": null,
      "name": "dim_github_action_usage.parquet",
      "path": "dim_github_action_usage.parquet",
      "size": 925071,
      "type": "file",
      "writable": true
    }
  ],
  "created": "2025-04-11T06:43:13.275909Z",
  "format": "json",
  "hash": null,
  "hash_algorithm": null,
  "last_modified": "2025-04-11T06:43:13.275909Z",
  "mimetype": null,
  "name": "",
  "path": "",
  "size": null,
  "type": "directory",
  "writable": true
}