{
  "content": [
    {
      "content": null,
      "created": "2024-05-24T06:31:36.746487Z",
      "format": null,
      "hash": null,
      "hash_algorithm": null,
      "last_modified": "2024-05-24T06:31:23.126422Z",
      "mimetype": null,
      "name": "dim_github_action_usage.parquet",
      "path": "dim_github_action_usage.parquet",
      "size": 444420,
      "type": "file",
      "writable": true
    },
    {
      "content": null,
      "created": "2024-05-24T06:31:36.750487Z",
      "format": null,
      "hash": null,
      "hash_algorithm": null,
      "last_modified": "2024-05-24T06:31:36.750487Z",
      "mimetype": null,
      "name": "reports",
      "path": "reports",
      "size": null,
      "type": "directory",
      "writable": true
    },
    {
      "content": null,
      "created": "2024-05-24T06:31:36.746487Z",
      "format": null,
      "hash": null,
      "hash_algorithm": null,
      "last_modified": "2024-05-24T06:31:22.398418Z",
      "mimetype": null,
      "name": "dim_dbt_repos.parquet",
      "path": "dim_dbt_repos.parquet",
      "size": 25184,
      "type": "file",
      "writable": true
    },
    {
      "content": null,
      "created": "2024-05-24T06:31:36.746487Z",
      "format": null,
      "hash": null,
      "hash_algorithm": null,
      "last_modified": "2024-05-24T06:31:23.046422Z",
      "mimetype": null,
      "name": "dim_medium_authors.parquet",
      "path": "dim_medium_authors.parquet",
      "size": 202962,
      "type": "file",
      "writable": true
    },
    {
      "content": null,
      "created": "2024-05-24T06:31:36.750487Z",
      "format": null,
      "hash": null,
      "hash_algorithm": null,
      "last_modified": "2024-05-24T06:31:22.462418Z",
      "mimetype": null,
      "name": "fct_medium_blogs_per_day.parquet",
      "path": "fct_medium_blogs_per_day.parquet",
      "size": 9092,
      "type": "file",
      "writable": true
    },
    {
      "content": null,
      "created": "2024-05-24T06:31:36.746487Z",
      "format": null,
      "hash": null,
      "hash_algorithm": null,
      "last_modified": "2024-05-24T06:31:22.450418Z",
      "mimetype": null,
      "name": "dim_dbt_discussions.parquet",
      "path": "dim_dbt_discussions.parquet",
      "size": 29742,
      "type": "file",
      "writable": true
    },
    {
      "content": null,
      "created": "2024-05-24T06:31:36.746487Z",
      "format": null,
      "hash": null,
      "hash_algorithm": null,
      "last_modified": "2024-05-24T06:31:22.474418Z",
      "mimetype": null,
      "name": "fct_dbt_interactors.parquet",
      "path": "fct_dbt_interactors.parquet",
      "size": 178760,
      "type": "file",
      "writable": true
    },
    {
      "content": null,
      "created": "2024-05-24T06:31:36.746487Z",
      "format": null,
      "hash": null,
      "hash_algorithm": null,
      "last_modified": "2024-05-24T06:31:23.074422Z",
      "mimetype": null,
      "name": "fct_medium_blogs.parquet",
      "path": "fct_medium_blogs.parquet",
      "size": 654657,
      "type": "file",
      "writable": true
    },
    {
      "content": null,
      "created": "2024-05-24T06:31:36.750487Z",
      "format": null,
      "hash": null,
      "hash_algorithm": null,
      "last_modified": "2024-05-24T06:31:35.042480Z",
      "mimetype": null,
      "name": "jupyter-lite.ipynb",
      "path": "jupyter-lite.ipynb",
      "size": 159963,
      "type": "notebook",
      "writable": true
    }
  ],
  "created": "2024-05-24T06:31:36.750487Z",
  "format": "json",
  "hash": null,
  "hash_algorithm": null,
  "last_modified": "2024-05-24T06:31:36.750487Z",
  "mimetype": null,
  "name": "",
  "path": "",
  "size": null,
  "type": "directory",
  "writable": true
}