{
  "content": [
    {
      "content": null,
      "created": "2025-05-02T06:42:38.767400Z",
      "format": null,
      "hash": null,
      "hash_algorithm": null,
      "last_modified": "2025-05-02T06:42:36.616413Z",
      "mimetype": null,
      "name": "jupyter-lite.ipynb",
      "path": "jupyter-lite.ipynb",
      "size": 160679,
      "type": "notebook",
      "writable": true
    },
    {
      "content": null,
      "created": "2025-05-02T06:42:38.762400Z",
      "format": null,
      "hash": null,
      "hash_algorithm": null,
      "last_modified": "2025-05-02T06:42:25.274479Z",
      "mimetype": null,
      "name": "dim_medium_authors.parquet",
      "path": "dim_medium_authors.parquet",
      "size": 327598,
      "type": "file",
      "writable": true
    },
    {
      "content": null,
      "created": "2025-05-02T06:42:38.759400Z",
      "format": null,
      "hash": null,
      "hash_algorithm": null,
      "last_modified": "2025-05-02T06:42:24.218485Z",
      "mimetype": null,
      "name": "dim_dbt_discussions.parquet",
      "path": "dim_dbt_discussions.parquet",
      "size": 38206,
      "type": "file",
      "writable": true
    },
    {
      "content": null,
      "created": "2025-05-02T06:42:38.764400Z",
      "format": null,
      "hash": null,
      "hash_algorithm": null,
      "last_modified": "2025-05-02T06:42:25.430478Z",
      "mimetype": null,
      "name": "fct_medium_blogs.parquet",
      "path": "fct_medium_blogs.parquet",
      "size": 1060695,
      "type": "file",
      "writable": true
    },
    {
      "content": null,
      "created": "2025-05-02T06:42:38.767400Z",
      "format": null,
      "hash": null,
      "hash_algorithm": null,
      "last_modified": "2025-05-02T06:42:38.767400Z",
      "mimetype": null,
      "name": "reports",
      "path": "reports",
      "size": null,
      "type": "directory",
      "writable": true
    },
    {
      "content": null,
      "created": "2025-05-02T06:42:38.763400Z",
      "format": null,
      "hash": null,
      "hash_algorithm": null,
      "last_modified": "2025-05-02T06:42:26.667470Z",
      "mimetype": null,
      "name": "fct_dbt_interactors.parquet",
      "path": "fct_dbt_interactors.parquet",
      "size": 220874,
      "type": "file",
      "writable": true
    },
    {
      "content": null,
      "created": "2025-05-02T06:42:38.767400Z",
      "format": null,
      "hash": null,
      "hash_algorithm": null,
      "last_modified": "2025-05-02T06:42:24.147485Z",
      "mimetype": null,
      "name": "fct_medium_blogs_per_day.parquet",
      "path": "fct_medium_blogs_per_day.parquet",
      "size": 13663,
      "type": "file",
      "writable": true
    },
    {
      "content": null,
      "created": "2025-05-02T06:42:38.760400Z",
      "format": null,
      "hash": null,
      "hash_algorithm": null,
      "last_modified": "2025-05-02T06:42:25.926475Z",
      "mimetype": null,
      "name": "dim_github_action_usage.parquet",
      "path": "dim_github_action_usage.parquet",
      "size": 953454,
      "type": "file",
      "writable": true
    },
    {
      "content": null,
      "created": "2025-05-02T06:42:38.759400Z",
      "format": null,
      "hash": null,
      "hash_algorithm": null,
      "last_modified": "2025-05-02T06:42:24.031486Z",
      "mimetype": null,
      "name": "dim_dbt_repos.parquet",
      "path": "dim_dbt_repos.parquet",
      "size": 27020,
      "type": "file",
      "writable": true
    }
  ],
  "created": "2025-05-02T06:42:38.767400Z",
  "format": "json",
  "hash": null,
  "hash_algorithm": null,
  "last_modified": "2025-05-02T06:42:38.767400Z",
  "mimetype": null,
  "name": "",
  "path": "",
  "size": null,
  "type": "directory",
  "writable": true
}