{
  "content": [
    {
      "content": null,
      "created": "2024-10-25T06:37:19.413193Z",
      "format": null,
      "hash": null,
      "hash_algorithm": null,
      "last_modified": "2024-10-25T06:37:09.041208Z",
      "mimetype": null,
      "name": "fct_medium_blogs_per_day.parquet",
      "path": "fct_medium_blogs_per_day.parquet",
      "size": 11103,
      "type": "file",
      "writable": true
    },
    {
      "content": null,
      "created": "2024-10-25T06:37:19.409193Z",
      "format": null,
      "hash": null,
      "hash_algorithm": null,
      "last_modified": "2024-10-25T06:37:08.789208Z",
      "mimetype": null,
      "name": "dim_medium_authors.parquet",
      "path": "dim_medium_authors.parquet",
      "size": 269185,
      "type": "file",
      "writable": true
    },
    {
      "content": null,
      "created": "2024-10-25T06:37:19.413193Z",
      "format": null,
      "hash": null,
      "hash_algorithm": null,
      "last_modified": "2024-10-25T06:37:17.505196Z",
      "mimetype": null,
      "name": "jupyter-lite.ipynb",
      "path": "jupyter-lite.ipynb",
      "size": 160315,
      "type": "notebook",
      "writable": true
    },
    {
      "content": null,
      "created": "2024-10-25T06:37:19.409193Z",
      "format": null,
      "hash": null,
      "hash_algorithm": null,
      "last_modified": "2024-10-25T06:37:09.461207Z",
      "mimetype": null,
      "name": "dim_github_action_usage.parquet",
      "path": "dim_github_action_usage.parquet",
      "size": 672431,
      "type": "file",
      "writable": true
    },
    {
      "content": null,
      "created": "2024-10-25T06:37:19.413193Z",
      "format": null,
      "hash": null,
      "hash_algorithm": null,
      "last_modified": "2024-10-25T06:37:19.413193Z",
      "mimetype": null,
      "name": "reports",
      "path": "reports",
      "size": null,
      "type": "directory",
      "writable": true
    },
    {
      "content": null,
      "created": "2024-10-25T06:37:19.409193Z",
      "format": null,
      "hash": null,
      "hash_algorithm": null,
      "last_modified": "2024-10-25T06:37:09.353207Z",
      "mimetype": null,
      "name": "fct_dbt_interactors.parquet",
      "path": "fct_dbt_interactors.parquet",
      "size": 201669,
      "type": "file",
      "writable": true
    },
    {
      "content": null,
      "created": "2024-10-25T06:37:19.413193Z",
      "format": null,
      "hash": null,
      "hash_algorithm": null,
      "last_modified": "2024-10-25T06:37:09.061208Z",
      "mimetype": null,
      "name": "fct_medium_blogs.parquet",
      "path": "fct_medium_blogs.parquet",
      "size": 848655,
      "type": "file",
      "writable": true
    },
    {
      "content": null,
      "created": "2024-10-25T06:37:19.405193Z",
      "format": null,
      "hash": null,
      "hash_algorithm": null,
      "last_modified": "2024-10-25T06:37:08.057209Z",
      "mimetype": null,
      "name": "dim_dbt_repos.parquet",
      "path": "dim_dbt_repos.parquet",
      "size": 28084,
      "type": "file",
      "writable": true
    },
    {
      "content": null,
      "created": "2024-10-25T06:37:19.405193Z",
      "format": null,
      "hash": null,
      "hash_algorithm": null,
      "last_modified": "2024-10-25T06:37:08.777208Z",
      "mimetype": null,
      "name": "dim_dbt_discussions.parquet",
      "path": "dim_dbt_discussions.parquet",
      "size": 33349,
      "type": "file",
      "writable": true
    }
  ],
  "created": "2024-10-25T06:37:19.413193Z",
  "format": "json",
  "hash": null,
  "hash_algorithm": null,
  "last_modified": "2024-10-25T06:37:19.413193Z",
  "mimetype": null,
  "name": "",
  "path": "",
  "size": null,
  "type": "directory",
  "writable": true
}