[
    {
        "author_name": "Amįń",
        "author_url": "https://medium.com/@aminsiddique95",
        "published_at": "2025-11-26 05:32:07.922000",
        "reading_time_minutes": 2.649056603773585,
        "story_url": "https://medium.com/@aminsiddique95/revolutionize-your-dbt-alerts-native-email-notifications-in-databricks-without-notebooks-or-70dba3e0094b",
        "subtitle": "How to Seamlessly Trigger Custom Email Alerts from dbt Using Unity Catalog Functions and SMTP (and Why This Hack Only Works in Databricks )",
        "title": "Revolutionize Your dbt Alerts: Native Email Notifications in Databricks Without Notebooks or…",
        "extraction_id": "b7ba3440-5e0d-4c4c-bdcd-b6cf342c402c",
        "extracted_at": "2025-11-28 06:33:05.143318",
        "extracted_at_epoch": 1764311585,
        "extraction_url": "https://medium.com/tag/dbt/archive",
        "tag": "dbt"
    },
    {
        "author_name": "Sendoa Moronta",
        "author_url": "https://medium.com/@sendoamoronta",
        "published_at": "2025-11-20 08:24:34.173000",
        "reading_time_minutes": 6.30188679245283,
        "story_url": "https://medium.com/@sendoamoronta/beyond-sql-predictive-compilation-and-adaptive-runtime-in-dbt-core-with-python-models-1d17e5b2d75d",
        "subtitle": "How Predictive Compilation and Adaptive Runtime with Python Models Are Transforming dbt Core into an Intelligent Data Orchestration Engine",
        "title": "Beyond SQL: Predictive Compilation and Adaptive Runtime in dbt Core with Python Models",
        "extraction_id": "b7ba3440-5e0d-4c4c-bdcd-b6cf342c402c",
        "extracted_at": "2025-11-28 06:33:05.143318",
        "extracted_at_epoch": 1764311585,
        "extraction_url": "https://medium.com/tag/dbt/archive",
        "tag": "dbt"
    },
    {
        "author_name": "Nikulsinh Rajput",
        "author_url": "https://medium.com/@hadiyolworld007",
        "published_at": "2025-11-21 05:32:07.086000",
        "reading_time_minutes": 5.49811320754717,
        "story_url": "https://medium.com/@hadiyolworld007/olap-without-the-warehouse-designing-a-duckdb-centric-analytics-architecture-596f7100301e",
        "subtitle": "How to get warehouse-style analytics — joins, aggregations, models — without renting a single cloud cluster.",
        "title": "OLAP Without the Warehouse: Designing a DuckDB-Centric Analytics Architecture",
        "extraction_id": "b7ba3440-5e0d-4c4c-bdcd-b6cf342c402c",
        "extracted_at": "2025-11-28 06:33:05.143318",
        "extracted_at_epoch": 1764311585,
        "extraction_url": "https://medium.com/tag/dbt/archive",
        "tag": "dbt"
    },
    {
        "author_name": "Clay Gambetti",
        "author_url": "https://medium.com/@cmgambetti",
        "published_at": "2025-11-24 15:56:25.598000",
        "reading_time_minutes": 9.278616352201258,
        "story_url": "https://blog.dataengineerthings.org/8-hours-to-clarity-understanding-dbt-e000816a0007",
        "subtitle": "A beginner’s deep dive into the data build tool transforming modern analytics",
        "title": "8 Hours to Clarity: Understanding dbt",
        "extraction_id": "b7ba3440-5e0d-4c4c-bdcd-b6cf342c402c",
        "extracted_at": "2025-11-28 06:33:05.143318",
        "extracted_at_epoch": 1764311585,
        "extraction_url": "https://medium.com/tag/dbt/archive",
        "tag": "dbt"
    },
    {
        "author_name": "Anwar",
        "author_url": "https://medium.com/@anwarmohammedbasha",
        "published_at": "2025-11-20 08:45:57.386000",
        "reading_time_minutes": 2.0226415094339623,
        "story_url": "https://medium.com/@anwarmohammedbasha/getting-started-with-dbt-using-duckdb-3c6e0de774ae",
        "subtitle": "dbt (Data Build Tool) is one of the simplest and most powerful tools for transforming data. It sits between your raw data and your…",
        "title": "Getting Started With dbt Using DuckDB: A Simple, Beginner-Friendly Guide",
        "extraction_id": "b7ba3440-5e0d-4c4c-bdcd-b6cf342c402c",
        "extracted_at": "2025-11-28 06:33:05.143318",
        "extracted_at_epoch": 1764311585,
        "extraction_url": "https://medium.com/tag/dbt/archive",
        "tag": "dbt"
    },
    {
        "author_name": "Quellin",
        "author_url": "https://medium.com/@npavfan2facts",
        "published_at": "2025-11-20 07:32:04.592000",
        "reading_time_minutes": 6.181132075471698,
        "story_url": "https://medium.com/@npavfan2facts/7-duckdb-dbt-tests-that-catch-data-drift-08b20414c569",
        "subtitle": "Practical test patterns to spot silent data breakage before it hits dashboards and models.",
        "title": "7 DuckDB + dbt Tests That Catch Data Drift",
        "extraction_id": "b7ba3440-5e0d-4c4c-bdcd-b6cf342c402c",
        "extracted_at": "2025-11-28 06:33:05.143318",
        "extracted_at_epoch": 1764311585,
        "extraction_url": "https://medium.com/tag/dbt/archive",
        "tag": "dbt"
    },
    {
        "author_name": "bluebirz",
        "author_url": "https://medium.com/@bluebirz",
        "published_at": "2025-11-25 00:00:59.820000",
        "reading_time_minutes": 5.076415094339622,
        "story_url": "https://medium.com/@bluebirz/lets-try-dbt-part-6-snapshots-and-analyses-4b4a7391912e",
        "subtitle": "Now we can create snapshots to track history and analyses to observe data",
        "title": "Let’s try: dbt part 6 — snapshots and analyses",
        "extraction_id": "b7ba3440-5e0d-4c4c-bdcd-b6cf342c402c",
        "extracted_at": "2025-11-28 06:33:05.143318",
        "extracted_at_epoch": 1764311585,
        "extraction_url": "https://medium.com/tag/dbt/archive",
        "tag": "dbt"
    },
    {
        "author_name": "Praneeth KD",
        "author_url": "https://medium.com/@praneeth7853",
        "published_at": "2025-11-23 11:58:02.990000",
        "reading_time_minutes": 0.9962264150943396,
        "story_url": "https://medium.com/@praneeth7853/7-snowflake-skills-that-will-make-you-a-top-10-data-engineer-in-2025-f2f8ce46b913",
        "subtitle": "You don’t need to “become a data scientist” to stay relevant.",
        "title": "7 Snowflake Skills That Will Make You a Top 10% Data Engineer in 2025",
        "extraction_id": "b7ba3440-5e0d-4c4c-bdcd-b6cf342c402c",
        "extracted_at": "2025-11-28 06:33:05.143318",
        "extracted_at_epoch": 1764311585,
        "extraction_url": "https://medium.com/tag/dbt/archive",
        "tag": "dbt"
    },
    {
        "author_name": "Abhishek Kumar Gupta",
        "author_url": "https://medium.com/@abhishekkrgupta0",
        "published_at": "2025-11-22 12:46:31.527000",
        "reading_time_minutes": 3.5839622641509434,
        "story_url": "https://medium.com/@abhishekkrgupta0/mastering-dbt-deployment-multi-environment-ci-cd-and-promotion-strategies-2fd18239e3f2",
        "subtitle": "Introduction",
        "title": "Mastering dbt Deployment: Multi-Environment, CI/CD, and Promotion Strategies",
        "extraction_id": "b7ba3440-5e0d-4c4c-bdcd-b6cf342c402c",
        "extracted_at": "2025-11-28 06:33:05.143318",
        "extracted_at_epoch": 1764311585,
        "extraction_url": "https://medium.com/tag/dbt/archive",
        "tag": "dbt"
    },
    {
        "author_name": "Riya Khandelwal",
        "author_url": "https://medium.com/@riyukhandelwal",
        "published_at": "2025-11-19 13:03:08.696000",
        "reading_time_minutes": 8.091509433962264,
        "story_url": "https://medium.com/@riyukhandelwal/connecting-dbt-workflow-with-snowflake-data-4bf3e451cc91",
        "subtitle": "This article talks about how to load the Snowflake Raw data in DBT, data transformation using DBT tools and further loading the transformed…",
        "title": "Connecting DBT workflow with Snowflake data",
        "extraction_id": "b7ba3440-5e0d-4c4c-bdcd-b6cf342c402c",
        "extracted_at": "2025-11-28 06:33:05.143318",
        "extracted_at_epoch": 1764311585,
        "extraction_url": "https://medium.com/tag/dbt/archive",
        "tag": "dbt"
    },
    {
        "author_name": "Abhishek Kumar Gupta",
        "author_url": "https://medium.com/@abhishekkrgupta0",
        "published_at": "2025-11-21 12:42:23.213000",
        "reading_time_minutes": 6.6716981132075475,
        "story_url": "https://medium.com/tech-with-abhishek/mastering-dbt-observability-monitoring-alerting-and-slas-for-analytics-pipelines-a6704dcd01b3",
        "subtitle": "Modern analytics pipelines are only as valuable as they are reliable. Stakeholders care less about how elegant the SQL is and more about…",
        "title": "Mastering dbt Observability: Monitoring, Alerting, and SLAs for Analytics Pipelines",
        "extraction_id": "b7ba3440-5e0d-4c4c-bdcd-b6cf342c402c",
        "extracted_at": "2025-11-28 06:33:05.143318",
        "extracted_at_epoch": 1764311585,
        "extraction_url": "https://medium.com/tag/dbt/archive",
        "tag": "dbt"
    },
    {
        "author_name": "Annesha Das",
        "author_url": "https://medium.com/@annesha.das94",
        "published_at": "2025-11-27 17:49:20.140000",
        "reading_time_minutes": 6.014150943396227,
        "story_url": "https://medium.com/@annesha.das94/from-full-refresh-to-smart-refresh-the-dbt-incremental-shift-8e0a4710a4fb",
        "subtitle": "Data today feels endless. It pours in from products, apps, sensors, logs and every digital touchpoint imaginable. For most teams, the…",
        "title": "From Full Refresh to Smart Refresh: The dbt Incremental Shift",
        "extraction_id": "b7ba3440-5e0d-4c4c-bdcd-b6cf342c402c",
        "extracted_at": "2025-11-28 06:33:05.143318",
        "extracted_at_epoch": 1764311585,
        "extraction_url": "https://medium.com/tag/dbt/archive",
        "tag": "dbt"
    },
    {
        "author_name": "Abhishek Kumar Gupta",
        "author_url": "https://medium.com/@abhishekkrgupta0",
        "published_at": "2025-11-26 08:52:23.480000",
        "reading_time_minutes": 6.6141509433962264,
        "story_url": "https://medium.com/tech-with-abhishek/optimizing-dbt-performance-at-scale-threading-incrementals-warehouse-tuning-and-dag-design-8e77e08d461a",
        "subtitle": "High-quality models are useless if they are too slow or too expensive to run at scale. As your dbt project grows—more models, more data…",
        "title": "Optimizing dbt Performance at Scale: Threading, Incrementals, Warehouse Tuning, and DAG Design",
        "extraction_id": "b7ba3440-5e0d-4c4c-bdcd-b6cf342c402c",
        "extracted_at": "2025-11-28 06:33:05.143318",
        "extracted_at_epoch": 1764311585,
        "extraction_url": "https://medium.com/tag/dbt/archive",
        "tag": "dbt"
    },
    {
        "author_name": "Nikulsinh Rajput",
        "author_url": "https://medium.com/@hadiyolworld007",
        "published_at": "2025-11-20 04:56:26.958000",
        "reading_time_minutes": 6.264150943396227,
        "story_url": "https://medium.com/@hadiyolworld007/duckdb-meets-dbt-redefining-what-production-grade-analytics-looks-like-on-a-laptop-d05e77179967",
        "subtitle": "How pairing DuckDB and dbt turns your laptop into a serious, testable analytics stack — without a warehouse budget.",
        "title": "DuckDB Meets dbt: Redefining What “Production-Grade” Analytics Looks Like on a Laptop",
        "extraction_id": "b7ba3440-5e0d-4c4c-bdcd-b6cf342c402c",
        "extracted_at": "2025-11-28 06:33:05.143318",
        "extracted_at_epoch": 1764311585,
        "extraction_url": "https://medium.com/tag/dbt/archive",
        "tag": "dbt"
    },
    {
        "author_name": "Kateryna",
        "author_url": "https://medium.com/@drogaieva",
        "published_at": "2025-11-27 04:42:40.856000",
        "reading_time_minutes": 4,
        "story_url": "https://drogaieva.medium.com/data-archaeology-the-art-and-science-of-discovering-useful-and-trustworthy-data-8f3b09637e88",
        "subtitle": "In mature organizations, data resembles archaeological strata — layers of information left behind by years of changing systems, teams, and…",
        "title": "Data Archaeology: The Art and Science of Discovering Useful and Trustworthy Data",
        "extraction_id": "b7ba3440-5e0d-4c4c-bdcd-b6cf342c402c",
        "extracted_at": "2025-11-28 06:33:05.143318",
        "extracted_at_epoch": 1764311585,
        "extraction_url": "https://medium.com/tag/dbt/archive",
        "tag": "dbt"
    },
    {
        "author_name": "Suellen Mouta",
        "author_url": "https://medium.com/@suellen.mouta",
        "published_at": "2025-11-23 17:30:07.316000",
        "reading_time_minutes": 2.449056603773585,
        "story_url": "https://medium.com/@suellen.mouta/como-construi-um-pipeline-de-dados-completo-usando-airflow-dbt-e-postgres-a-partir-de-uma-api-793057c6634e",
        "subtitle": "Introdução",
        "title": "Como construi um Pipeline de Dados completo usando Airflow, DBT e Postgres a partir de uma API…",
        "extraction_id": "b7ba3440-5e0d-4c4c-bdcd-b6cf342c402c",
        "extracted_at": "2025-11-28 06:33:05.143318",
        "extracted_at_epoch": 1764311585,
        "extraction_url": "https://medium.com/tag/dbt/archive",
        "tag": "dbt"
    },
    {
        "author_name": "Neurobyte",
        "author_url": "https://medium.com/@kaushalsinh73",
        "published_at": "2025-11-27 16:32:27.858000",
        "reading_time_minutes": 5.09433962264151,
        "story_url": "https://medium.com/@kaushalsinh73/duckdb-in-airflow-dbt-reproducible-analytics-without-spark-45380ba47b58",
        "subtitle": "How to build a modern, testable analytics stack on Parquet and SQL — without standing up a Spark cluster.",
        "title": "DuckDB in Airflow + dbt: Reproducible Analytics Without Spark",
        "extraction_id": "b7ba3440-5e0d-4c4c-bdcd-b6cf342c402c",
        "extracted_at": "2025-11-28 06:33:05.143318",
        "extracted_at_epoch": 1764311585,
        "extraction_url": "https://medium.com/tag/dbt/archive",
        "tag": "dbt"
    },
    {
        "author_name": "Shravani Hariprasad",
        "author_url": "https://medium.com/@hariprasadshravani",
        "published_at": "2025-11-25 01:51:18.311000",
        "reading_time_minutes": 7.790880503144654,
        "story_url": "https://medium.com/@hariprasadshravani/building-a-complete-dbt-bigquery-analytics-workflow-c36599eae051",
        "subtitle": "dbt (Data Build Tool) has become the central brain for analytics engineering. If you’re working with BigQuery and want to implement clean…",
        "title": "Building a Complete dbt + BigQuery Analytics Workflow",
        "extraction_id": "b7ba3440-5e0d-4c4c-bdcd-b6cf342c402c",
        "extracted_at": "2025-11-28 06:33:05.143318",
        "extracted_at_epoch": 1764311585,
        "extraction_url": "https://medium.com/tag/dbt/archive",
        "tag": "dbt"
    },
    {
        "author_name": "akatekhanh",
        "author_url": "https://medium.com/@akatekhanh",
        "published_at": "2025-11-18 15:13:04.107000",
        "reading_time_minutes": 7.640880503144654,
        "story_url": "https://blog.dataengineerthings.org/we-use-spark-and-dbt-for-catalog-federation-ingestion-and-etl-4a224ad48c43",
        "subtitle": "Running DBT on Spark when your data lives everywhere. Unified data cataloging with federating catalogs.",
        "title": "We use Spark and DBT for Catalog Federation, Ingestion and ETL",
        "extraction_id": "b7ba3440-5e0d-4c4c-bdcd-b6cf342c402c",
        "extracted_at": "2025-11-28 06:33:05.143318",
        "extracted_at_epoch": 1764311585,
        "extraction_url": "https://medium.com/tag/dbt/archive",
        "tag": "dbt"
    },
    {
        "author_name": "Javier Mones",
        "author_url": "https://medium.com/@javirmones",
        "published_at": "2025-11-18 21:31:31.931000",
        "reading_time_minutes": 5.058805031446541,
        "story_url": "https://medium.com/@javirmones/como-incluir-dbt-checkpoint-en-dbt-cloud-y-no-morir-en-el-intento-462ac014e37b",
        "subtitle": "Recientemente me he tenido que enfrentar a la odisea de incluir dbt checkpoint junto a dbt Cloud, para comprobar si los modelos y las…",
        "title": "Como incluir dbt-checkpoint en dbt Cloud y no morir en el intento",
        "extraction_id": "b7ba3440-5e0d-4c4c-bdcd-b6cf342c402c",
        "extracted_at": "2025-11-28 06:33:05.143318",
        "extracted_at_epoch": 1764311585,
        "extraction_url": "https://medium.com/tag/dbt/archive",
        "tag": "dbt"
    }
]